Workbook

Sheet Inputs
A1: INPUTS — blue cells are inputs; every other sheet computes from them. Prices budgetary ±30% until quoted.
A2: technician rate /h | B2: 38
A3: loaded multiplier | B3: 1.6
A4: productive hours /wk | B4: 32
A5: weeks per year | B5: 48
A6: depreciation years | B6: 3
A7: overhead per set | B7: 2
A8: scrap fraction | B8: 0.05
A9: horizon weeks | B9: 40
A10: selling price per set | B10: 95
A11: equipment capital (buy now) | B11: 2600
A12: NRE one-time total | B12: 2185.6
A14: volumes (sets/week)
A15: 5
A16: 15
A17: 22.5
A18: 30

Sheet BOM
A1: MPN | B1: qty/set | C1: unit price | D1: note | E1: ext/set (=qty*price*(1+scrap))
A2: BNC-STR-58 | B2: 1 | C2: 1.9 | D2: tier at 1440/yr, +5% scrap | E2: =IF(C2="",0,B2*C2*(1+Inputs!$B$8))
A3: C-RG174 | B3: 1.2 | C3: 0.55 | D3: tier at 1728/yr, +5% scrap | E3: =IF(C3="",0,B3*C3*(1+Inputs!$B$8))
A4: DSUB-9S | B4: 1 | C4: 1.4 | D4: tier at 1440/yr, +5% scrap | E4: =IF(C4="",0,B4*C4*(1+Inputs!$B$8))
A5: FER-174 | B5: 1 | C5: 0.18 | D5: tier at 1440/yr, +5% scrap | E5: =IF(C5="",0,B5*C5*(1+Inputs!$B$8))
A6: HS-1248 | B6: 0.04 | C6: 2.1 | D6: tier at 57.6/yr, +5% scrap | E6: =IF(C6="",0,B6*C6*(1+Inputs!$B$8))
A7: PIN-SMA-174 | B7: 1 | C7: 0.4 | D7: tier at 1440/yr, +5% scrap | E7: =IF(C7="",0,B7*C7*(1+Inputs!$B$8))
A8: SMA-STR-174 | B8: 1 | C8: 2.9 | D8: tier at 1440/yr, +5% scrap | E8: =IF(C8="",0,B8*C8*(1+Inputs!$B$8))
A9: W-HOOK-22 | B9: 1.5 | C9: 0.07 | D9: tier at 2160/yr, +5% scrap | E9: =IF(C9="",0,B9*C9*(1+Inputs!$B$8))
D10: MATERIAL PER SET | E10: =SUM(E2:E9)

Sheet Labor
A1: harness | B1: qty/set | C1: Cutting / stripping | D1: Cable preparation (shield / coax prep) | E1: Crimp / solder | F1: Connector assembly | G1: Layout / tape / label | H1: Test / inspect / pack | I1: min/harness (sum) | J1: min contributed/set
A2: G-2001 | B2: 1 | C2: 0.8 | D2: 3 | E2: 3 | F2: 2.3 | G2: 2.4 | H2: 2.2 | I2: =SUM(C2:H2) | J2: =B2*I2
A3: G-2002 | B3: 1 | C3: 2.4 | D3: 0 | E3: 9 | F3: 2 | G3: 4.3 | H3: 2.3 | I3: =SUM(C3:H3) | J3: =B3*I3
I4: MIN PER SET | J4: =SUM(J2:J3)
A5: Station minutes are planning estimates (A-TIME) — overwrite blue cells with measured values when available.

Sheet Cost
A1: volume (sets/wk) | B1: material/set | C1: labor direct/set | D1: labor loaded/set | E1: depreciation/set | F1: NRE/set | G1: overhead/set | H1: TOTAL/set
A2: 5 | B2: =BOM!$E$10 | C2: =Labor!$J$4/60*Inputs!$B$2 | D2: =C2*Inputs!$B$3 | E2: =Inputs!$B$11/(Inputs!$B$6*Inputs!$B$5)/A2 | F2: =Inputs!$B$12/(A2*Inputs!$B$9) | G2: =Inputs!$B$7 | H2: =B2+D2+E2+F2+G2
A3: 15 | B3: =BOM!$E$10 | C3: =Labor!$J$4/60*Inputs!$B$2 | D3: =C3*Inputs!$B$3 | E3: =Inputs!$B$11/(Inputs!$B$6*Inputs!$B$5)/A3 | F3: =Inputs!$B$12/(A3*Inputs!$B$9) | G3: =Inputs!$B$7 | H3: =B3+D3+E3+F3+G3
A4: 22.5 | B4: =BOM!$E$10 | C4: =Labor!$J$4/60*Inputs!$B$2 | D4: =C4*Inputs!$B$3 | E4: =Inputs!$B$11/(Inputs!$B$6*Inputs!$B$5)/A4 | F4: =Inputs!$B$12/(A4*Inputs!$B$9) | G4: =Inputs!$B$7 | H4: =B4+D4+E4+F4+G4
A5: 30 | B5: =BOM!$E$10 | C5: =Labor!$J$4/60*Inputs!$B$2 | D5: =C5*Inputs!$B$3 | E5: =Inputs!$B$11/(Inputs!$B$6*Inputs!$B$5)/A5 | F5: =Inputs!$B$12/(A5*Inputs!$B$9) | G5: =Inputs!$B$7 | H5: =B5+D5+E5+F5+G5

Sheet Capacity
A1: volume | B1: hours/week | C1: technicians (ceil) | D1: share of a 4-tech shift
A2: =Cost!A2 | B2: =A2*Labor!$J$4/60 | C2: =CEILING(B2/Inputs!$B$4,1) | D2: =C2/4
A3: =Cost!A3 | B3: =A3*Labor!$J$4/60 | C3: =CEILING(B3/Inputs!$B$4,1) | D3: =C3/4
A4: =Cost!A4 | B4: =A4*Labor!$J$4/60 | C4: =CEILING(B4/Inputs!$B$4,1) | D4: =C4/4
A5: =Cost!A5 | B5: =A5*Labor!$J$4/60 | C5: =CEILING(B5/Inputs!$B$4,1) | D5: =C5/4

Sheet Margin
A1: volume | B1: cost/set | C1: GM/set | D1: GM % | E1: GM/year
A2: =Cost!A2 | B2: =Cost!H2 | C2: =Inputs!$B$10-B2 | D2: =C2/Inputs!$B$10 | E2: =C2*A2*Inputs!$B$5
A3: =Cost!A3 | B3: =Cost!H3 | C3: =Inputs!$B$10-B3 | D3: =C3/Inputs!$B$10 | E3: =C3*A3*Inputs!$B$5
A4: =Cost!A4 | B4: =Cost!H4 | C4: =Inputs!$B$10-B4 | D4: =C4/Inputs!$B$10 | E4: =C4*A4*Inputs!$B$5
A5: =Cost!A5 | B5: =Cost!H5 | C5: =Inputs!$B$10-B5 | D5: =C5/Inputs!$B$10 | E5: =C5*A5*Inputs!$B$5

Sheet Assumptions
A1: id | B1: assumption | C1: value | D1: impact | E1: status | F1: source
A2: A-VOL-G | B2: Volumes are in SETS per week | D2: all outputs | E2: confirmed | F2: [unverified: owner statement]
A3: A-SOLDER | B3: Hand solder, SAC305, iron 370 C; class 2 workmanship | D3: solder time standards and inspection | E3: open | F3: [unverified: shop default]
A4: A-TIME | B4: station unit times are planning estimates until measured (±25% carried in margin sensitivity) | E4: open
A5: A-TOOL-T | B5: hand crimp 1.5 min, press 0.25 min, solder 3.0 min per termination | E5: open
A6: A-CAL | B6: external calibration 120/event | E6: open
A7: A-FAI | B7: first article + qualification 2 weeks | E7: open
A8: A-TRAIN | B8: training 1 week / 8 h | E8: open
A9: A-SHIFT | B9: second shift above 4 technicians | E9: open
A10: A-FB-SHIELD | B10: 25 mm shield fold-back allowance on shielded ends | E10: open
