Workbook

Sheet Inputs
A1: INPUTS — blue cells are inputs; every other sheet computes from them. Prices budgetary ±30% until quoted.
A2: technician rate /h | B2: 38
A3: loaded multiplier | B3: 1.6
A4: productive hours /wk | B4: 32
A5: weeks per year | B5: 48
A6: depreciation years | B6: 3
A7: overhead per set | B7: 4
A8: scrap fraction | B8: 0.03
A9: horizon weeks | B9: 52
A10: selling price per set | B10: 410
A11: equipment capital (buy now) | B11: 6500
A12: NRE one-time total | B12: 2722
A14: volumes (sets/week)
A15: 10
A16: 30
A17: 50
A18: 75
A19: 100

Sheet BOM
A1: MPN | B1: qty/set | C1: unit price | D1: note | E1: ext/set (=qty*price*(1+scrap))
A2: CONN-MAT-ECU | B2: 2 | C2: 1.6 | D2: tier at 9600/yr, +3% scrap | E2: =IF(C2="",0,B2*C2*(1+Inputs!$B$8))
A3: CONN-NANO-4 | B3: 3 | C3: 0.6 | D3: tier at 14400/yr, +3% scrap | E3: =IF(C3="",0,B3*C3*(1+Inputs!$B$8))
A4: FIXEL-01 | B4: 2 | C4: 0.12 | D4: tier at 9600/yr, +3% scrap | E4: =IF(C4="",0,B4*C4*(1+Inputs!$B$8))
A5: HSG-DTM-2P | B5: 3 | C5: 0.9 | D5: tier at 14400/yr, +3% scrap | E5: =IF(C5="",0,B5*C5*(1+Inputs!$B$8))
A6: HSG-DTM-2S | B6: 2 | C6: 0.9 | D6: tier at 9600/yr, +3% scrap | E6: =IF(C6="",0,B6*C6*(1+Inputs!$B$8))
A7: HSG-GC-2 | B7: 1 | C7: 0.5 | D7: tier at 4800/yr, +3% scrap | E7: =IF(C7="",0,B7*C7*(1+Inputs!$B$8))
A8: INSERT-M12 | B8: 3 | C8: 2.4 | D8: tier at 14400/yr, +3% scrap | E8: =IF(C8="",0,B8*C8*(1+Inputs!$B$8))
A9: LBL-01 | B9: 2 | C9: 0.02 | D9: tier at 9600/yr, +3% scrap | E9: =IF(C9="",0,B9*C9*(1+Inputs!$B$8))
A10: PLUG-DTM-16 | B10: 3 | C10: 0.06 | D10: tier at 14400/yr, +3% scrap | E10: =IF(C10="",0,B10*C10*(1+Inputs!$B$8))
A11: PTA-ETH-2M | B11: 2 | C11: 11.9 | D11: tier at 9600/yr, +3% scrap | E11: =IF(C11="",0,B11*C11*(1+Inputs!$B$8))
A12: RCPT-GC-075 | B12: 1 | C12: 0.18 | D12: tier at 4800/yr, +3% scrap | E12: =IF(C12="",0,B12*C12*(1+Inputs!$B$8))
A13: SHLD-BRL-01 | B13: 2 | C13: 0.35 | D13: tier at 9600/yr, +3% scrap | E13: =IF(C13="",0,B13*C13*(1+Inputs!$B$8))
... A25: WEDGE-DTM-2 | B25: 5 | C25: 0.22 | D25: tier at 24000/yr, +3% scrap | E25: =IF(C25="",0,B25*C25*(1+Inputs!$B$8))
D26: MATERIAL PER SET | E26: =SUM(E2:E25)

Sheet Labor
A1: harness | B1: qty/set | C1: Cutting / stripping | D1: Cable preparation (shield / coax prep) | E1: Crimp / solder | F1: Connector assembly | G1: Layout / tape / label | H1: Test / inspect / pack | I1: min/harness (sum) | J1: min contributed/set
A2: D-1001 | B2: 1 | C2: 0 | D2: 0 | E2: 0 | F2: 1 | G2: 4 | H2: 2 | I2: =SUM(C2:H2) | J2: =B2*I2
A3: D-1002 | B3: 2 | C3: 0 | D3: 2.5 | E3: 3 | F3: 2 | G3: 2 | H3: 5.2 | I3: =SUM(C3:H3) | J3: =B3*I3
A4: D-1003 | B4: 1 | C4: 2.4 | D4: 0 | E4: 9 | F4: 4 | G4: 3.2 | H4: 2.6 | I4: =SUM(C4:H4) | J4: =B4*I4
A5: D-1004 | B5: 1 | C5: 1.6 | D5: 0 | E5: 6 | F5: 3 | G5: 2.4 | H5: 2.4 | I5: =SUM(C5:H5) | J5: =B5*I5
A6: D-1005 | B6: 1 | C6: 2.4 | D6: 0 | E6: 4.5 | F6: 3 | G6: 10.7 | H6: 2.3 | I6: =SUM(C6:H6) | J6: =B6*I6
A7: D-1006 | B7: 1 | C7: 2.4 | D7: 0 | E7: 9 | F7: 4.5 | G7: 4.8 | H7: 2.6 | I7: =SUM(C7:H7) | J7: =B7*I7
A8: D-1007 | B8: 2 | C8: 0.8 | D8: 0 | E8: 1.5 | F8: 1 | G8: 0.6 | H8: 2.1 | I8: =SUM(C8:H8) | J8: =B8*I8
I9: MIN PER SET | J9: =SUM(J2:J8)
A10: Station minutes are planning estimates (A-TIME) — overwrite blue cells with measured values when available.

Sheet Cost
A1: volume (sets/wk) | B1: material/set | C1: labor direct/set | D1: labor loaded/set | E1: depreciation/set | F1: NRE/set | G1: overhead/set | H1: TOTAL/set
A2: 10 | B2: =BOM!$E$26 | C2: =Labor!$J$9/60*Inputs!$B$2 | D2: =C2*Inputs!$B$3 | E2: =Inputs!$B$11/(Inputs!$B$6*Inputs!$B$5)/A2 | F2: =Inputs!$B$12/(A2*Inputs!$B$9) | G2: =Inputs!$B$7 | H2: =B2+D2+E2+F2+G2
A3: 30 | B3: =BOM!$E$26 | C3: =Labor!$J$9/60*Inputs!$B$2 | D3: =C3*Inputs!$B$3 | E3: =Inputs!$B$11/(Inputs!$B$6*Inputs!$B$5)/A3 | F3: =Inputs!$B$12/(A3*Inputs!$B$9) | G3: =Inputs!$B$7 | H3: =B3+D3+E3+F3+G3
A4: 50 | B4: =BOM!$E$26 | C4: =Labor!$J$9/60*Inputs!$B$2 | D4: =C4*Inputs!$B$3 | E4: =Inputs!$B$11/(Inputs!$B$6*Inputs!$B$5)/A4 | F4: =Inputs!$B$12/(A4*Inputs!$B$9) | G4: =Inputs!$B$7 | H4: =B4+D4+E4+F4+G4
A5: 75 | B5: =BOM!$E$26 | C5: =Labor!$J$9/60*Inputs!$B$2 | D5: =C5*Inputs!$B$3 | E5: =Inputs!$B$11/(Inputs!$B$6*Inputs!$B$5)/A5 | F5: =Inputs!$B$12/(A5*Inputs!$B$9) | G5: =Inputs!$B$7 | H5: =B5+D5+E5+F5+G5
A6: 100 | B6: =BOM!$E$26 | C6: =Labor!$J$9/60*Inputs!$B$2 | D6: =C6*Inputs!$B$3 | E6: =Inputs!$B$11/(Inputs!$B$6*Inputs!$B$5)/A6 | F6: =Inputs!$B$12/(A6*Inputs!$B$9) | G6: =Inputs!$B$7 | H6: =B6+D6+E6+F6+G6

Sheet Capacity
A1: volume | B1: hours/week | C1: technicians (ceil) | D1: share of a 4-tech shift
A2: =Cost!A2 | B2: =A2*Labor!$J$9/60 | C2: =CEILING(B2/Inputs!$B$4,1) | D2: =C2/4
A3: =Cost!A3 | B3: =A3*Labor!$J$9/60 | C3: =CEILING(B3/Inputs!$B$4,1) | D3: =C3/4
A4: =Cost!A4 | B4: =A4*Labor!$J$9/60 | C4: =CEILING(B4/Inputs!$B$4,1) | D4: =C4/4
A5: =Cost!A5 | B5: =A5*Labor!$J$9/60 | C5: =CEILING(B5/Inputs!$B$4,1) | D5: =C5/4
A6: =Cost!A6 | B6: =A6*Labor!$J$9/60 | C6: =CEILING(B6/Inputs!$B$4,1) | D6: =C6/4

Sheet MakeVsBuy
A1: volume | B1: make/set (=Cost) | C1: buy/set incl. gap | D1: weekly diff (buy-make) | E1: annual diff
A2: =Cost!A2 | B2: =Cost!H2 | C2: 310 | D2: =(C2-B2)*A2 | E2: =D2*Inputs!$B$5
A3: =Cost!A3 | B3: =Cost!H3 | C3: 310 | D3: =(C3-B3)*A3 | E3: =D3*Inputs!$B$5
A4: =Cost!A4 | B4: =Cost!H4 | C4: 310 | D4: =(C4-B4)*A4 | E4: =D4*Inputs!$B$5
A5: =Cost!A5 | B5: =Cost!H5 | C5: 310 | D5: =(C5-B5)*A5 | E5: =D5*Inputs!$B$5
A6: =Cost!A6 | B6: =Cost!H6 | C6: 310 | D6: =(C6-B6)*A6 | E6: =D6*Inputs!$B$5
A7: buy/set is the quote plus our gap estimate — see the make-vs-buy report; blue = overwrite with final quote

Sheet Margin
A1: volume | B1: cost/set | C1: GM/set | D1: GM % | E1: GM/year
A2: =Cost!A2 | B2: =Cost!H2 | C2: =Inputs!$B$10-B2 | D2: =C2/Inputs!$B$10 | E2: =C2*A2*Inputs!$B$5
A3: =Cost!A3 | B3: =Cost!H3 | C3: =Inputs!$B$10-B3 | D3: =C3/Inputs!$B$10 | E3: =C3*A3*Inputs!$B$5
A4: =Cost!A4 | B4: =Cost!H4 | C4: =Inputs!$B$10-B4 | D4: =C4/Inputs!$B$10 | E4: =C4*A4*Inputs!$B$5
A5: =Cost!A5 | B5: =Cost!H5 | C5: =Inputs!$B$10-B5 | D5: =C5/Inputs!$B$10 | E5: =C5*A5*Inputs!$B$5
A6: =Cost!A6 | B6: =Cost!H6 | C6: =Inputs!$B$10-B6 | D6: =C6/Inputs!$B$10 | E6: =C6*A6*Inputs!$B$5

Sheet Assumptions
A1: id | B1: assumption | C1: value | D1: impact | E1: status | F1: source
A2: A-VOL | B2: Volumes are in SETS per week (owner confirmed; lesson 8) | D2: all capacity and cost outputs | E2: confirmed | F2: [unverified: owner statement]
A3: A-RATES | B3: Technician $38/h, loaded 1.6x, 32 productive h/week, 48 weeks/year | D3: labor cost and capacity | E3: confirmed | F3: [unverified: owner statement]
A4: A-SCRAP | B4: 3% material scrap allowance at prototype volume | D4: material cost and order quantities | E4: open | F4: [unverified: shop default]
A5: A-TIME | B5: station unit times are planning estimates until measured (±25% carried in margin sensitivity) | E5: open
A6: A-TOOL-T | B6: hand crimp 1.5 min, press 0.25 min, solder 3.0 min per termination | E6: open
A7: A-CAL | B7: external calibration 120/event | E7: open
A8: A-FAI | B8: first article + qualification 2 weeks | E8: open
A9: A-TRAIN | B9: training 1 week / 8 h | E9: open
A10: A-SHIFT | B10: second shift above 4 technicians | E10: open
A11: A-FB-SHIELD | B11: 25 mm shield fold-back allowance on shielded ends | E11: open
